dgs/__init__.py
dgs/diagrams.py
dgs/diagrams_cmd.py
dgs/ngwebserver.py
dgs/version.py
dgs/webserver.py
diagrams_examples/example.circo
diagrams_examples/example.dot
diagrams_examples/example.fdp
diagrams_examples/example.mscgen
diagrams_examples/example.neato
diagrams_examples/example.osage
diagrams_examples/example.patchwork
diagrams_examples/example.plantuml
diagrams_examples/example.sfdp
diagrams_examples/example.twopi
online_diagrams-0.1.1.dist-info/METADATA
online_diagrams-0.1.1.dist-info/WHEEL
online_diagrams-0.1.1.dist-info/entry_points.txt
online_diagrams-0.1.1.dist-info/licenses/LICENSE
online_diagrams-0.1.1.dist-info/RECORD
