Metadata-Version: 2.1
Name: online-diagrams
Version: 0.1.1
Summary: nicegui based online diagrams rendering tool for e.g. plantuml and graphviz
Project-URL: Home, https://github.com/BITPlan/diagrams
Project-URL: Documentation, http://wiki.bitplan.com/index.php/Diagrams
Project-URL: Source, https://github.com/BITPlan/diagrams
Author-email: Wolfgang Fahl <wf@bitplan.com>
Maintainer-email: Wolfgang Fahl <wf@bitplan.com>
License-Expression: Apache-2.0
License-File: LICENSE
Keywords: graphviz,nicegui,plantuml
Classifier: Development Status :: 4 - Beta
Classifier: Environment :: Console
Classifier: Intended Audience :: Developers
Classifier: Intended Audience :: Education
Classifier: License :: OSI Approved :: Apache Software License
Classifier: Operating System :: OS Independent
Classifier: Programming Language :: Python :: 3 :: Only
Classifier: Programming Language :: Python :: 3.9
Classifier: Programming Language :: Python :: 3.10
Classifier: Programming Language :: Python :: 3.11
Classifier: Topic :: Software Development :: Libraries :: Python Modules
Requires-Python: >=3.9
Requires-Dist: flask
Requires-Dist: ngwidgets>=0.6.3
Requires-Dist: pydantic>=2.4.2
Provides-Extra: test
Requires-Dist: green; extra == 'test'
